anyqueue.py
anyqueue-0.0.0.dist-info/METADATA
anyqueue-0.0.0.dist-info/WHEEL
anyqueue-0.0.0.dist-info/licenses/LICENSE
anyqueue-0.0.0.dist-info/RECORD
