Metadata-Version: 2.1
Name: anyqueue
Version: 0.0.0
Summary: Coming soon.
Author-email: Pydantic Team <hello@pydantic.dev>
License-Expression: MIT
License-File: LICENSE
Classifier: Development Status :: 1 - Planning
Classifier: Topic :: Internet
